motionpicture/__init__.py
motionpicture/argparse.py
motionpicture/mopi.py
motionpicture/moviemaker.py
motionpicture-0.3.1.dist-info/entry_points.txt
motionpicture-0.3.1.dist-info/LICENSE
motionpicture-0.3.1.dist-info/WHEEL
motionpicture-0.3.1.dist-info/METADATA
motionpicture-0.3.1.dist-info/RECORD
