Metadata-Version: 2.1
Name: motionpicture
Version: 0.3.1
Summary: Make animations with Python
Home-page: https://github.com/sbozzolo/motionpicture
License: GPL-3.0-or-later
Author: Gabriele Bozzola
Author-email: gabrielebozzola@arizona.edu
Maintainer: Gabriele Bozzola
Maintainer-email: gabrielebozzola@arizona.edu
Requires-Python: >=3.6.2,<3.11
Classifier: License :: OSI Approved :: GNU General Public License v3 or later (GPLv3+)
Classifier: Programming Language :: Python :: 3
Classifier: Programming Language :: Python :: 3.10
Classifier: Programming Language :: Python :: 3.7
Classifier: Programming Language :: Python :: 3.8
Classifier: Programming Language :: Python :: 3.9
Requires-Dist: ConfigArgParse (>=1.0.0,<2.0.0)
Requires-Dist: ffmpeg-python (>=0.1.0,<0.2.0)
Requires-Dist: python-magic (>=0.4.27,<0.5.0)
Requires-Dist: tqdm (>=4.0.0,<5.0.0)
Project-URL: Bug Tracker, https://github.com/sbozzolo/motionpicture/issues
Project-URL: Repository, https://github.com/sbozzolo/motionpicture
